telegram_text/__init__.py
telegram_text/bases.py
telegram_text/custom.py
telegram_text/elements.py
telegram_text/markdown.py
telegram_text/styles.py
telegram_text-0.1.2.dist-info/LICENSE
telegram_text-0.1.2.dist-info/METADATA
telegram_text-0.1.2.dist-info/WHEEL
telegram_text-0.1.2.dist-info/RECORD
