Metadata-Version: 2.1
Name: telegram-text
Version: 0.1.2
Summary: Python markup module for Telegram messenger. This module provides a rich list of components to build any possible markup fast and render it to specific html or MarkdownV2 formats.
Home-page: https://telegram-text.alinsky.tech
License: MIT
Keywords: telegram,markup,markdown,formating
Author: Vladimir Alinsky
Author-email: Vladimir@Alinsky.tech
Requires-Python: >=3.7,<4.0
Classifier: Development Status :: 5 - Production/Stable
Classifier: License :: OSI Approved :: MIT License
Classifier: Programming Language :: Python :: 3
Classifier: Programming Language :: Python :: 3.7
Classifier: Programming Language :: Python :: 3.8
Classifier: Programming Language :: Python :: 3.9
Classifier: Programming Language :: Python :: 3.10
Classifier: Programming Language :: Python :: 3.11
Project-URL: Repository, https://github.com/SKY-ALIN/telegram-text
